label_studio_paddleocr/__init__.py
label_studio_paddleocr/__main__.py
label_studio_paddleocr/_wsgi.py
label_studio_paddleocr/config.py
label_studio_paddleocr/model.py
label_studio_paddleocr-0.2.0.dist-info/WHEEL
label_studio_paddleocr-0.2.0.dist-info/entry_points.txt
label_studio_paddleocr-0.2.0.dist-info/METADATA
label_studio_paddleocr-0.2.0.dist-info/RECORD
