Metadata-Version: 2.3
Name: label-studio-paddleocr
Version: 0.2.0
Summary: Integrate Label Studio with PaddleOCR-VL
Author: Roger Chen
Author-email: Roger Chen <chenrui@gmail.com>
Requires-Dist: gunicorn>=23.0.0
Requires-Dist: label-studio-ml
Requires-Dist: pip-system-certs>=5.3
Requires-Dist: pydantic-settings[yaml]>=2.12.0
Requires-Python: >=3.13
